[
    {
        "GooglePlaceId": "ChIJMTUKb65WKhMRYIM0uO7i4co",
        "Name": "Il Trip per Tre",
        "Latitude": 43.7742113,
        "Longitude": 11.2433225
    },
    {
        "GooglePlaceId": "ChIJU8bONalWKhMRAvzfvnkE4-E",
        "Name": "The Joshua Tree Pub",
        "Latitude": 43.77451809999999,
        "Longitude": 11.246937
    },
    {
        "GooglePlaceId": "ChIJ4RIuLqpWKhMRVtsyq-Uwd0Y",
        "Name": "Daunbailo' Irish Pub",
        "Latitude": 43.7723813,
        "Longitude": 11.2500876
    },
    {
        "GooglePlaceId": "ChIJK807NABUKhMRIvH3c-7pp6s",
        "Name": "The Old Stove Irish Pub",
        "Latitude": 43.7699319,
        "Longitude": 11.2536542
    },
    {
        "GooglePlaceId": "ChIJpSUk6hZXKhMRaIfUCe5tTlU",
        "Name": "The White Lion",
        "Latitude": 43.77895609999999,
        "Longitude": 11.2389408
    },
    {
        "GooglePlaceId": "ChIJcdLqJ6hWKhMRgHa6NJoYsKk",
        "Name": "Dublin Pub",
        "Latitude": 43.7754248,
        "Longitude": 11.2523946
    },
    {
        "GooglePlaceId": "ChIJIwpcWKlWKhMRwT4CRKchkb8",
        "Name": "Public House 27",
        "Latitude": 43.77319989999999,
        "Longitude": 11.2475542
    },
    {
        "GooglePlaceId": "ChIJ77C2LxxUKhMR_Fjs3AlpBlo",
        "Name": "The Florence Irish Pub",
        "Latitude": 43.7816573,
        "Longitude": 11.2561866
    },
    {
        "GooglePlaceId": "ChIJg5e7X6tWKhMRU_6qLt-s6Js",
        "Name": "One Eyed Jack",
        "Latitude": 43.7694419,
        "Longitude": 11.2468705
    },
    {
        "GooglePlaceId": "ChIJK-71yARXKhMRs6dxvz6g_3U",
        "Name": "Pub Lo Stregatto",
        "Latitude": 43.775279,
        "Longitude": 11.2432666
    },
    {
        "GooglePlaceId": "ChIJZ-T6gKlWKhMRD7n-_BjcTwA",
        "Name": "The Fiddler's Elbow Irish Pub",
        "Latitude": 43.773111,
        "Longitude": 11.2498656
    },
    {
        "GooglePlaceId": "ChIJkeAJz6xWKhMR7mFMuOBzzbI",
        "Name": "The Hidden Pub",
        "Latitude": 43.7692256,
        "Longitude": 11.2446834
    },
    {
        "GooglePlaceId": "ChIJ4-flEwFUKhMRrUmkRt4GAIs",
        "Name": "King Grizzly",
        "Latitude": 43.770947,
        "Longitude": 11.255994
    },
    {
        "GooglePlaceId": "ChIJ3UnAYJxVKhMR2MCss-N0Q1Q",
        "Name": "O'Hara's Pub Firenze",
        "Latitude": 43.772262,
        "Longitude": 11.2622952
    },
    {
        "GooglePlaceId": "ChIJrweOLMFVKhMRkdo_hGAbIeA",
        "Name": "BEER SPOT CRAFT PUB - Beer - Cocktail - Food",
        "Latitude": 43.7719769,
        "Longitude": 11.2615232
    },
    {
        "GooglePlaceId": "ChIJ27MvxYNXKhMRj1QPDiuOHQc",
        "Name": "Alibi Craft Beer & Kitchen",
        "Latitude": 43.7753182,
        "Longitude": 11.2524549
    },
    {
        "GooglePlaceId": "ChIJHaTVQ1NRKhMR_rzDhBVCpog",
        "Name": "Archea Brewery",
        "Latitude": 43.7674151,
        "Longitude": 11.2455325
    },
    {
        "GooglePlaceId": "ChIJFauRUeZVKhMRVPqWHZuMMX8",
        "Name": "Fitzpatrick's Irish Pub & Restaurant",
        "Latitude": 43.770473,
        "Longitude": 11.260265
    },
    {
        "GooglePlaceId": "ChIJxU3k3ghUKhMRoVt0bvM_46U",
        "Name": "The Book Pub",
        "Latitude": 43.7701865,
        "Longitude": 11.2664121
    },
    {
        "GooglePlaceId": "ChIJEQoXwhhTKhMRX1jsTi5m59Y",
        "Name": "JJ Cathedral",
        "Latitude": 43.77278279999999,
        "Longitude": 11.2547858
    }
]